Traffic Light Simulator/sequence_detector.v
module zero_one_detector(A,Y,clk,rst);
   input A;
   input clk;
   input rst;
   output  Y;

   parameter S0=2'b00;
   parameter S1=2'b01;
   parameter S2=2'b10;

   reg [1:0] currentstate;
   reg [1:0] nextstate;
 
always@(posedge clk,posedge rst)
      if(rst)
       begin
        currentstate<=S0;
        nextstate<=S0;
       end
      else
        begin
         if(A)
           begin
             if(currentstate==S1)
                  nextstate<=S2;
             else if(currentstate==S2) 
                  nextstate<=S0;
             else if(currentstate==S0)
                  nextstate<=S0;
           end
         else if(!A)
           begin
            if(currentstate==S1)
             nextstate<=S1;
            else if (currentstate==S2)
             nextstate<=S1;
            else if(currentstate==S0)
             nextstate<=S1;
           end
        currentstate<=nextstate;
        end     
     assign Y=(currentstate[0]);
endmodule

Traffic Light Simulator/sequence_detector_tb.v
module zero_one_detector_tb;

     reg A;
     reg rst;
     reg clk;

     wire Y;

     zero_one_detector uut(
     .A(A),
     .rst(rst),
     .clk(clk),
     .Y(Y)
     );
      
     initial begin
       $dumpfile("sequencedetector.vcd");
       $dumpvars(0,zero_one_detector_tb);
     end
     initial begin
          
        rst=1;
        #100
        rst=0;   //Initial time required for setup.
        clk=0;
        #100
        A=1;
        clk=1;
        #100
        A=0;
        clk=0;
        #100
        clk=1;
        #100
        A=1;
        clk=0;
        #100
        clk=1;
        #100
        A=1;
        clk=0;
        #100
        clk=1;
        #100
        clk=0;
        rst=1;
        #100
        clk=1;
        rst=0;
        #100
        clk=0;
   


      end
always@(*)
  $display("time=%d: clk=%b,A=%b,rst=%b Y=%b\n",$time,clk,A,rst,Y);

endmodule

Traffic Light Simulator/sequencedetector.vcd
$date
	Wed May  9 08:45:12 2018
$end
$version
	Icarus Verilog
$end
$timescale
	1s
$end
$scope module zero_one_detector_tb $end
$var wire 1 ! Y $end
$var reg 1 " A $end
$var reg 1 # clk $end
$var reg 1 $ rst $end
$scope module uut $end
$var wire 1 " A $end
$var wire 1 # clk $end
$var wire 1 $ rst $end
$var wire 1 ! Y $end
$var reg 2 % currentstate [1:0] $end
$var reg 2 & nextstate [1:0] $end
$upscope $end
$upscope $end
$enddefinitions $end
#0
$dumpvars
b0 &
b0 %
1$
x#
x"
0!
$end
#100
0#
0$
#200
1#
1"
#300
0#
0"
#400
b1 &
1#
#500
0#
1"
#600
1!
b1 %
b0 &
1#
#700
0#
#800
0!
b0 %
b10 &
1#
#900
b0 &
1$
0#
#1000
0$
1#
